deadrat/__init__.py
deadrat/py.typed
deadrat-0.0.3.dist-info/METADATA
deadrat-0.0.3.dist-info/WHEEL
deadrat-0.0.3.dist-info/licenses/LICENSE
deadrat-0.0.3.dist-info/RECORD
