Metadata-Version: 2.4
Name: deadrat
Version: 0.0.3
Summary: A Python wrapper for the DeadRat Bot API
Project-URL: Homepage, https://github.com/rerufa/deadrat_bot_framework
Project-URL: Documentation, https://rerufa.github.io/deadrat_bot_framework/
Author-email: Rainy351 <rainy3510@gmail.com>
License-Expression: MIT
License-File: LICENSE
Requires-Python: >=3.8
Requires-Dist: requests>=2.25.0
